investor_agent/__init__.py
investor_agent/server.py
iflow_mcp_ferdousbhai_investor_agent-1.6.3.dist-info/METADATA
iflow_mcp_ferdousbhai_investor_agent-1.6.3.dist-info/WHEEL
iflow_mcp_ferdousbhai_investor_agent-1.6.3.dist-info/entry_points.txt
iflow_mcp_ferdousbhai_investor_agent-1.6.3.dist-info/licenses/LICENSE
iflow_mcp_ferdousbhai_investor_agent-1.6.3.dist-info/RECORD
