Metadata-Version: 2.4
Name: iflow-mcp_ferdousbhai_investor-agent
Version: 1.6.3
Summary: A Model Context Protocol server for an investor agent
Author-email: Ferdous <ferdous@hey.com>
License-File: LICENSE
Keywords: finance,financial analysis,investment,mcp,model context protocol,stock market,technical analysis,trading,yfinance
Classifier: Intended Audience :: End Users/Desktop
Classifier: Intended Audience :: Financial and Insurance Industry
Classifier: License :: OSI Approved :: MIT License
Classifier: Programming Language :: Python :: 3.12
Classifier: Topic :: Office/Business :: Financial
Requires-Python: >=3.12
Requires-Dist: anysqlite>=0.0.5
Requires-Dist: hishel>=1.0.0
Requires-Dist: html5lib>=1.1
Requires-Dist: httpx>=0.28.1
Requires-Dist: lxml>=6.0.2
Requires-Dist: mcp[cli]>=1.19.0
Requires-Dist: numpy>=2.0
Requires-Dist: pandas>=2.3.3
Requires-Dist: pytrends>=4.9.2
Requires-Dist: requests-cache>=1.2.1
Requires-Dist: tenacity>=9.1.2
Requires-Dist: yfinance[nospam]>=0.2.66
Provides-Extra: ta
Requires-Dist: ta-lib>=0.6.8; extra == 'ta'
